{
	"Version": 3,
	"Meta": {
		"Duration": 2.983,
		"Fps": 60.0,
		"Loop": true,
		"AreBeziersRestricted": false,
		"CurveCount": 7,
		"TotalSegmentCount": 27,
		"TotalPointCount": 78,
		"UserDataCount": 0,
		"TotalUserDataSize": 0
	},
	"Curves": [
		{
			"Target": "Parameter",
			"Id": "Param69",
			"Segments": [
				0,
				0,
				0,
				2.983,
				0
			]
		},
		{
			"Target": "Parameter",
			"Id": "Param25",
			"Segments": [
				0,
				0,
				1,
				0.261,
				0,
				0.522,
				8.166,
				0.783,
				11,
				1,
				1.033,
				13.714,
				1.283,
				13.163,
				1.533,
				16,
				1,
				1.8,
				19.026,
				2.067,
				30,
				2.333,
				30,
				0,
				2.983,
				30
			]
		},
		{
			"Target": "Parameter",
			"Id": "Param26",
			"Segments": [
				0,
				0,
				0,
				0.65,
				0,
				1,
				0.911,
				0,
				1.172,
				8.638,
				1.433,
				11,
				1,
				1.683,
				13.261,
				1.933,
				12.63,
				2.183,
				15,
				1,
				2.45,
				17.528,
				2.717,
				30,
				2.983,
				30
			]
		},
		{
			"Target": "Parameter",
			"Id": "Param27",
			"Segments": [
				0,
				0,
				0,
				2.983,
				180
			]
		},
		{
			"Target": "Parameter",
			"Id": "Param70",
			"Segments": [
				0,
				0,
				0,
				2.983,
				180
			]
		},
		{
			"Target": "Parameter",
			"Id": "Param28",
			"Segments": [
				0,
				1,
				1,
				0.02,
				-1.258,
				0.2,
				-26,
				0.3,
				-26,
				1,
				0.422,
				-26,
				0.544,
				-13.81,
				0.667,
				1,
				1,
				0.8,
				17.156,
				0.933,
				22,
				1.067,
				22,
				1,
				1.194,
				22,
				1.322,
				16.463,
				1.45,
				1,
				1,
				1.583,
				-15.136,
				1.717,
				-26,
				1.85,
				-26,
				1,
				1.972,
				-26,
				2.094,
				-13.81,
				2.217,
				1,
				1,
				2.35,
				17.156,
				2.483,
				22,
				2.617,
				22,
				1,
				2.739,
				22,
				2.946,
				4.929,
				2.983,
				1
			]
		},
		{
			"Target": "Parameter",
			"Id": "Param30",
			"Segments": [
				0,
				25,
				1,
				0.084,
				19.974,
				0.2,
				16.27,
				0.3,
				1,
				1,
				0.422,
				-17.663,
				0.544,
				-26,
				0.667,
				-26,
				1,
				0.8,
				-26,
				0.933,
				-12.875,
				1.067,
				4,
				1,
				1.194,
				20.172,
				1.322,
				25,
				1.45,
				25,
				1,
				1.583,
				25,
				1.717,
				18.526,
				1.85,
				1,
				1,
				1.972,
				-15.066,
				2.094,
				-26,
				2.217,
				-26,
				1,
				2.35,
				-26,
				2.483,
				-13.371,
				2.617,
				4,
				1,
				2.739,
				19.924,
				2.842,
				19.902,
				2.983,
				25
			]
		}
	]
}